README.md
protococo.py
setup.py
protococo.egg-info/PKG-INFO
protococo.egg-info/SOURCES.txt
protococo.egg-info/dependency_links.txt
protococo.egg-info/entry_points.txt
protococo.egg-info/requires.txt
protococo.egg-info/top_level.txt