Metadata-Version: 1.1
Name: protococo
Version: 0.0.1
Summary: protococo helps you design, test and debug custom binary protocols
Home-page: https://github.com/alvarinyo/protococo
Author: Alvaro Luis Pierna
Author-email: alvaro.luispierna@gmail.com
License: MIT
Platform: UNKNOWN
Classifier: Development Status :: 4 - Beta
Classifier: Environment :: Console
Classifier: Intended Audience :: Developers
Classifier: License :: OSI Approved :: MIT License
Classifier: Operating System :: OS Independent
Classifier: Programming Language :: Python
Classifier: Topic :: Software Development
Classifier: Topic :: Utilities
